zenkat/__init__.py
zenkat/__main__.py
zenkat/default_config.py
zenkat/zenkat.py
zenkat/zk.py
zenkat-0.1.1.dist-info/LICENSE
zenkat-0.1.1.dist-info/METADATA
zenkat-0.1.1.dist-info/WHEEL
zenkat-0.1.1.dist-info/entry_points.txt
zenkat-0.1.1.dist-info/top_level.txt
zenkat-0.1.1.dist-info/RECORD
