Metadata-Version: 2.1
Name: zenkat
Version: 0.1.1
Summary: CLI tool to allow using flat files as a Zettelkasten system, similar to Obsidian.
Author-email: Frank Davies <frank@fd93.me>
Project-URL: Homepage, https://github.com/fdavies93/zenkat
Project-URL: Repository, https://github.com/fdavies93/zenkat
Classifier: Programming Language :: Python :: 3
Classifier: License :: OSI Approved :: GNU General Public License (GPL)
Classifier: Operating System :: OS Independent
Requires-Python: >=3.10
License-File: LICENSE
Requires-Dist: python-dateutil
Requires-Dist: PyYAML
Requires-Dist: rich
